enov8_mcp_server/__init__.py
enov8_mcp_server/__main__.py
enov8_mcp_server/server.py
enov8_mcp_server-0.1.0.dist-info/METADATA
enov8_mcp_server-0.1.0.dist-info/WHEEL
enov8_mcp_server-0.1.0.dist-info/entry_points.txt
enov8_mcp_server-0.1.0.dist-info/licenses/LICENSE
enov8_mcp_server-0.1.0.dist-info/RECORD
