Metadata-Version: 2.4
Name: enov8-mcp-server
Version: 0.1.0
Summary: MCP server for Enov8 ecosystem management platform
Project-URL: Homepage, https://github.com/yourusername/enov8-mcp-server
Project-URL: Documentation, https://github.com/yourusername/enov8-mcp-server#readme
Project-URL: Repository, https://github.com/yourusername/enov8-mcp-server
Project-URL: Issues, https://github.com/yourusername/enov8-mcp-server/issues
Author-email: Your Name <your.email@example.com>
License: MIT
License-File: LICENSE
Keywords: ecosystem-management,enov8,mcp,model-context-protocol
Classifier: Development Status :: 4 - Beta
Classifier: Intended Audience :: Developers
Classifier: License :: OSI Approved :: MIT License
Classifier: Programming Language :: Python :: 3
Classifier: Programming Language :: Python :: 3.10
Classifier: Programming Language :: Python :: 3.11
Classifier: Programming Language :: Python :: 3.12
Classifier: Programming Language :: Python :: 3.13
Requires-Python: >=3.10
Requires-Dist: fastmcp>=0.1.0
Requires-Dist: httpx>=0.25.0
Requires-Dist: python-dotenv>=1.0.0
